setup.cfg
setup.py
math_braid/__init__.py
math_braid/braid.py
math_braid/canonical_factor.py
math_braid/permutation.py
math_braid.egg-info/PKG-INFO
math_braid.egg-info/SOURCES.txt
math_braid.egg-info/dependency_links.txt
math_braid.egg-info/requires.txt
math_braid.egg-info/top_level.txt
math_braid/extras/braidextras.py
math_braid/extras/dihedral.py
math_braid/extras/group.py
math_braid/extras/modular.py
math_braid/extras/presentation.py
math_braid/extras/represent.py
math_braid/extras/simplify.py